README.md
setup.py
ising2D/__init__.py
ising2D/ising2D.py
ising2D.egg-info/PKG-INFO
ising2D.egg-info/SOURCES.txt
ising2D.egg-info/dependency_links.txt
ising2D.egg-info/requires.txt
ising2D.egg-info/top_level.txt